client/__init__.py
client/admin.py
client/case.py
client/customer.py
client/global_search.py
client/session.py
client/users.py
dfir-iris-client/__init__.py
dfir-iris-client/admin.py
dfir-iris-client/case.py
dfir-iris-client/customer.py
dfir-iris-client/global_search.py
dfir-iris-client/session.py
dfir-iris-client/users.py
dfir_iris_client/__init__.py
dfir_iris_client/admin.py
dfir_iris_client/alert.py
dfir_iris_client/case.py
dfir_iris_client/customer.py
dfir_iris_client/global_search.py
dfir_iris_client/session.py
dfir_iris_client/users.py
dfir_iris_client/helper/__init__.py
dfir_iris_client/helper/alert_status.py
dfir_iris_client/helper/analysis_status.py
dfir_iris_client/helper/assets_type.py
dfir_iris_client/helper/authorization.py
dfir_iris_client/helper/case_classifications.py
dfir_iris_client/helper/colors.py
dfir_iris_client/helper/compromise_status.py
dfir_iris_client/helper/doc_tracer.py
dfir_iris_client/helper/docker_helper.py
dfir_iris_client/helper/errors.py
dfir_iris_client/helper/events_categories.py
dfir_iris_client/helper/ioc_types.py
dfir_iris_client/helper/iris_object.py
dfir_iris_client/helper/objects_def.py
dfir_iris_client/helper/outcome_status.py
dfir_iris_client/helper/report_template_types.py
dfir_iris_client/helper/task_status.py
dfir_iris_client/helper/tlps.py
dfir_iris_client/helper/utils.py
dfir_iris_client/tests/__init__.py
dfir_iris_client/tests/conftest.py
dfir_iris_client/tests/test_admin.py
dfir_iris_client/tests/test_alert.py
dfir_iris_client/tests/test_alert_status.py
dfir_iris_client/tests/test_analysis_status.py
dfir_iris_client/tests/test_asset_type.py
dfir_iris_client/tests/test_authorization.py
dfir_iris_client/tests/test_case.py
dfir_iris_client/tests/test_case_classifications.py
dfir_iris_client/tests/test_compromise_status.py
dfir_iris_client/tests/test_customer.py
dfir_iris_client/tests/test_event_categories.py
dfir_iris_client/tests/test_global_search.py
dfir_iris_client/tests/test_ioc_types.py
dfir_iris_client-2.0.4.dist-info/LICENSE.txt
dfir_iris_client-2.0.4.dist-info/METADATA
dfir_iris_client-2.0.4.dist-info/WHEEL
dfir_iris_client-2.0.4.dist-info/top_level.txt
dfir_iris_client-2.0.4.dist-info/RECORD
