Metadata-Version: 2.1
Name: dfir-iris-client
Version: 2.0.4
Summary: Client for DFIR-IRIS API
Home-page: https://github.com/dfir-iris/dfir-iris-client
Author: DFIR-IRIS
Author-email: DFIR-IRIS <contact@dfir-iris.org>
Classifier: Programming Language :: Python :: 3
Classifier: License :: OSI Approved :: GNU Lesser General Public License v3 (LGPLv3)
Classifier: Operating System :: OS Independent
License-File: LICENSE.txt
Requires-Dist: requests
Requires-Dist: packaging
Requires-Dist: deprecated
